{
  "totalAmount": 1,
  "data": [
    {
      "id": 284054,
      "title": "Black Panther",
      "tagline": "Long live the king",
      "vote_average": 7.3,
      "vote_count": 3788,
      "release_date": "2018-02-13",
      "poster_path": "https://image.tmdb.org/t/p/w500/uxzzxijgPIY7slzFvMotPv8wjKA.jpg",
      "overview": "King T'Challa returns home from America to the reclusive, technologically advanced African nation of Wakanda to serve as his country's new leader. However, T'Challa soon finds that he is challenged for the throne by factions within his own country as well as without.  Using powers reserved to Wakandan kings, T'Challa assumes the Black Panther mantel to join with girlfriend Nakia, the queen-mother, his princess-kid sister,  members of the Dora Milaje (the Wakandan \"special forces\"), and an American secret agent, to prevent Wakanda from being dragged into a world war.",
      "budget": 200000000,
      "revenue": 1245257672,
      "genres": [
        "Action"
      ],
      "runtime": 134
    }
  ],
  "offset": 0,
  "limit": 10
}
